streamcpy.cp39-win_amd64.pyd
streamcpy-1.0.1.dist-info/LICENSE
streamcpy-1.0.1.dist-info/METADATA
streamcpy-1.0.1.dist-info/WHEEL
streamcpy-1.0.1.dist-info/top_level.txt
streamcpy-1.0.1.dist-info/RECORD
