Metadata-Version: 2.1
Name: streamcpy
Version: 1.0.1
Summary: The Stream Api in Python
Home-page: https://github.com/littlebutt/streamcpy
Author: littlebutt
Author-email: luogan1996@icloud.com
License: GPL-3.0 license
Platform: UNKNOWN
License-File: LICENSE
